latexexpr_efficalc/__init__.py
latexexpr_efficalc/sympy/__init__.py
latexexpr_efficalc-0.5.3.dist-info/LICENSE
latexexpr_efficalc-0.5.3.dist-info/METADATA
latexexpr_efficalc-0.5.3.dist-info/WHEEL
latexexpr_efficalc-0.5.3.dist-info/top_level.txt
latexexpr_efficalc-0.5.3.dist-info/RECORD
