Metadata-Version: 2.1
Name: latexexpr_efficalc
Version: 0.5.3
Summary: Module for easy LaTeX typesetting of algebraic expressions in symbolic form with automatic substitution and result computation.
Author-email: Andrew Young <youandvern@gmail.com>, Jakub Kaderka <jakub.kaderka@gmail.com>, Jan Stransky <jan.stransky.fsv.cvut.cz@gmail.com>
Project-URL: Homepage, https://github.com/youandvern/latexexpr_efficalc
Project-URL: Documentation, https://youandvern.github.io/latexexpr_efficalc
Project-URL: Issues, https://github.com/youandvern/latexexpr_efficalc/issues
Classifier: Programming Language :: Python :: 3
Classifier: License :: OSI Approved :: GNU Lesser General Public License v3 (LGPLv3)
Classifier: Operating System :: OS Independent
Requires-Python: >=3.10
License-File: LICENSE
